LICENSE.MIT
MANIFEST.in
README.md
setup.py
sophiabus230/__init__.py
sophiabus230.egg-info/PKG-INFO
sophiabus230.egg-info/SOURCES.txt
sophiabus230.egg-info/dependency_links.txt
sophiabus230.egg-info/not-zip-safe
sophiabus230.egg-info/requires.txt
sophiabus230.egg-info/top_level.txt
sophiabus230/tests/example_content.html