Metadata-Version: 1.0
Name: sophiabus230
Version: 0.1
Summary: Module to get the timetable of the Sophia Antipolis bus line 230
Home-page: http://github.com/paraita/sophiabus230
Author: Paraita Wohler
Author-email: paraita.wohler@gmail.com
License: MIT
Platform: UNKNOWN
